whitebit/__init__.py
whitebit/whitebit_api_order_book_data_source.py
whitebit/whitebit_api_user_stream_data_source.py
whitebit/whitebit_auth.py
whitebit/whitebit_constants.py
whitebit/whitebit_exchange.py
whitebit/whitebit_utils.py
whitebit/whitebit_web_utils.py
whitebit_connector-0.1.0.dist-info/METADATA
whitebit_connector-0.1.0.dist-info/WHEEL
whitebit_connector-0.1.0.dist-info/top_level.txt
whitebit_connector-0.1.0.dist-info/RECORD
